actonet/__init__.py
actonet/gc.py
actonet-1.0.dist-info/METADATA
actonet-1.0.dist-info/WHEEL
actonet-1.0.dist-info/top_level.txt
actonet-1.0.dist-info/RECORD
